[
    {
        "key": "dbln",
        "value": "%7B%22100005016548455%22%3A%22bco9SZEn%22%7D",
        "domain": "facebook.com",
        "path": "/login/device-based/",
        "hostOnly": false,
        "creation": "2025-07-06T03:52:09.013Z",
        "lastAccessed": "2025-07-06T03:52:09.013Z"
    },
    {
        "key": "datr",
        "value": "ofJpaCnWLrs6Uf5YOR34WNrR",
        "domain": "facebook.com",
        "path": "/",
        "hostOnly": false,
        "creation": "2025-07-06T03:52:09.013Z",
        "lastAccessed": "2025-07-06T03:52:09.013Z"
    },
    {
        "key": "sb",
        "value": "ofJpaCIKwcDkxDZtG9j6s3Ls",
        "domain": "facebook.com",
        "path": "/",
        "hostOnly": false,
        "creation": "2025-07-06T03:52:09.013Z",
        "lastAccessed": "2025-07-06T03:52:09.013Z"
    },
    {
        "key": "dpr",
        "value": "1.734286904335022",
        "domain": "facebook.com",
        "path": "/",
        "hostOnly": false,
        "creation": "2025-07-06T03:52:09.013Z",
        "lastAccessed": "2025-07-06T03:52:09.013Z"
    },
    {
        "key": "wd",
        "value": "953x1881",
        "domain": "facebook.com",
        "path": "/",
        "hostOnly": false,
        "creation": "2025-07-06T03:52:09.013Z",
        "lastAccessed": "2025-07-06T03:52:09.013Z"
    },
    {
        "key": "c_user",
        "value": "100005016548455",
        "domain": "facebook.com",
        "path": "/",
        "hostOnly": false,
        "creation": "2025-07-06T03:52:09.013Z",
        "lastAccessed": "2025-07-06T03:52:09.013Z"
    },
    {
        "key": "xs",
        "value": "19%3AqRGqK3mQOfUJNg%3A2%3A1751773871%3A-1%3A-1",
        "domain": "facebook.com",
        "path": "/",
        "hostOnly": false,
        "creation": "2025-07-06T03:52:09.013Z",
        "lastAccessed": "2025-07-06T03:52:09.013Z"
    },
    {
        "key": "ps_l",
        "value": "1",
        "domain": "facebook.com",
        "path": "/",
        "hostOnly": false,
        "creation": "2025-07-06T03:52:09.013Z",
        "lastAccessed": "2025-07-06T03:52:09.013Z"
    },
    {
        "key": "ps_n",
        "value": "1",
        "domain": "facebook.com",
        "path": "/",
        "hostOnly": false,
        "creation": "2025-07-06T03:52:09.013Z",
        "lastAccessed": "2025-07-06T03:52:09.013Z"
    },
    {
        "key": "fr",
        "value": "0vRjn9lHvX1E54Zs4.AWdOIGD9ivxKznrlNZMa1aUalRDi-qnr6AidblXwUkcyMhXLItw.BoafKh..AAA.0.0.BoafLN.AWfSedFE3XxD6PA9rAOTay1z6xg",
        "domain": "facebook.com",
        "path": "/",
        "hostOnly": false,
        "creation": "2025-07-06T03:52:09.013Z",
        "lastAccessed": "2025-07-06T03:52:09.013Z"
    },
    {
        "key": "presence",
        "value": "C%7B%22t3%22%3A%5B%5D%2C%22utc3%22%3A1751773911938%2C%22v%22%3A1%7D",
        "domain": "facebook.com",
        "path": "/",
        "hostOnly": false,
        "creation": "2025-07-06T03:52:09.013Z",
        "lastAccessed": "2025-07-06T03:52:09.013Z"
    }
]
